{
  "culture": "es",
  "translations": {
    "No pivot data to display.": "No hay datos de tabla dinámica para mostrar.",
    "No value fields are declared.": "No se han declarado campos de valores.",
    "No data to display.": "No hay datos para mostrar.",
    "Grand Total": "Total general",
    "Total": "Total",
    "Values": "Valores",
    "Fields": "Campos",
    "Available fields": "Campos disponibles",
    "Drag and drop fields to arrange": "Arrastre y suelte campos para organizarlos",
    "Drop field here": "Suelte el campo aquí",
    "Rows": "Filas",
    "Columns": "Columnas",
    "Filters": "Filtros",
    "Apply": "Aplicar",
    "Cancel": "Cancelar",
    "All": "Todos",
    "Aggregate": "Agregado",
    "Count": "Recuento",
    "CountNonNull": "Recuento no nulo",
    "Sum": "Suma",
    "Average": "Promedio",
    "Min": "Mín",
    "Max": "Máx",
    "Pagination": "Paginación",
    "First": "Primera",
    "Prev": "Anterior",
    "Next": "Siguiente",
    "Last": "Última",
    "items per page": "elementos por página",
    "{0} - {1} of {2} items": "{0} - {1} de {2} elementos"
  }
}