{
  "culture": "ru",
  "translations": {
    "No pivot data to display.": "Нет сводных данных для отображения.",
    "No value fields are declared.": "Поля значений не объявлены.",
    "No data to display.": "Нет данных для отображения.",
    "Grand Total": "Общий итог",
    "Total": "Итого",
    "Values": "Значения",
    "Fields": "Поля",
    "Available fields": "Доступные поля",
    "Drag and drop fields to arrange": "Перетащите поля для упорядочивания",
    "Drop field here": "Перетащите поле сюда",
    "Rows": "Строки",
    "Columns": "Столбцы",
    "Filters": "Фильтры",
    "Apply": "Применить",
    "Cancel": "Отмена",
    "All": "Все",
    "Aggregate": "Агрегация",
    "Count": "Количество",
    "CountNonNull": "Количество непустых",
    "Sum": "Сумма",
    "Average": "Среднее",
    "Min": "Мин",
    "Max": "Макс",
    "Pagination": "Пагинация",
    "First": "Первая",
    "Prev": "Предыдущая",
    "Next": "Следующая",
    "Last": "Последняя",
    "items per page": "элементов на страницу",
    "{0} - {1} of {2} items": "{0} - {1} из {2} элементов"
  }
}